mailerpy/__init__.py
mailerpy/mailer.py
mailerpy-0.1.0.dist-info/LICENSE.txt
mailerpy-0.1.0.dist-info/METADATA
mailerpy-0.1.0.dist-info/WHEEL
mailerpy-0.1.0.dist-info/top_level.txt
mailerpy-0.1.0.dist-info/RECORD
