Metadata-Version: 2.1
Name: mailerpy
Version: 0.1.0
Summary: A package to send mail
Home-page: https://github.com/Rabindra-Sapkota/mailer
Author: Rabindra Sapkota
Author-email: rabindrasapkota2@gmail.com
License: UNKNOWN
Platform: UNKNOWN
Classifier: Programming Language :: Python :: 3
Classifier: License :: OSI Approved :: MIT License
Classifier: Operating System :: OS Independent
Requires-Python: >=3.6
